README.md
setup.py
yaml_injection.py
yaml_injection.egg-info/PKG-INFO
yaml_injection.egg-info/SOURCES.txt
yaml_injection.egg-info/dependency_links.txt
yaml_injection.egg-info/not-zip-safe
yaml_injection.egg-info/requires.txt
yaml_injection.egg-info/top_level.txt